winfspy/__init__.py
winfspy/_version.py
winfspy/file_system.py
winfspy/memfs.py
winfspy/operations.py
winfspy/plumbing/__init__.py
winfspy/plumbing/_bindings.pyd
winfspy/plumbing/bindings.py
winfspy/plumbing/exceptions.py
winfspy/plumbing/file_attribute.py
winfspy/plumbing/file_system_interface.py
winfspy/plumbing/get_winfsp_dir.py
winfspy/plumbing/security_descriptor.py
winfspy/plumbing/service.py
winfspy/plumbing/status.py
winfspy/plumbing/win32_filetime.py
winfspy/tests/__init__.py
winfspy/tests/fixtures.py
winfspy/tests/test_bindings.py
winfspy/tests/test_security_descriptor.py
winfspy/tests/winfsp_tests/__init__.py
winfspy/tests/winfsp_tests/__main__.py
winfspy/tests/winfsp_tests/conftest.py
winfspy/tests/winfsp_tests/test_winfsp_tests.py
winfspy/tests/winfstest/__init__.py
winfspy/tests/winfstest/__main__.py
winfspy/tests/winfstest/conftest.py
winfspy/tests/winfstest/test_winfs.py
winfspy/tests/winfstest/cases/00_CreateFile_Dispositions.t
winfspy/tests/winfstest/cases/01_CreateFile_Attributes.t
winfspy/tests/winfstest/cases/02_CreateRemoveDirectory.t
winfspy/tests/winfstest/cases/03_FindFiles.t
winfspy/tests/winfstest/cases/04_MoveFile.t
winfspy/tests/winfstest/cases/05_CreateFile_Truncation.t
winfspy/tests/winfstest/cases/06_FileTimes.t
winfspy/tests/winfstest/cases/07_SetGetFileAttributes.t
winfspy/tests/winfstest/cases/08_CreateFile_Delete.t
winfspy/tests/winfstest/cases/09_CreateFile_Sharing.t
winfspy/tests/winfstest/cases/10_GetSetSecurity.t
winfspy-0.8.4.dist-info/METADATA
winfspy-0.8.4.dist-info/WHEEL
winfspy-0.8.4.dist-info/top_level.txt
winfspy-0.8.4.dist-info/RECORD
