Metadata-Version: 2.1
Name: winfspy
Version: 0.8.4
Summary: CFFI bindings for WinFSP
Home-page: https://github.com/Scille/winfspy
Author: Emmanuel Leblond
Author-email: emmanuel.leblond@gmail.com
License: UNKNOWN
Platform: UNKNOWN
Classifier: Development Status :: 4 - Beta
Classifier: Operating System :: Microsoft :: Windows
Classifier: Programming Language :: Python :: 3
Classifier: Programming Language :: Python :: 3.7
Classifier: Programming Language :: Python :: 3.8
Classifier: Programming Language :: Python :: 3.9
Classifier: Programming Language :: Python :: 3.10
Classifier: License :: OSI Approved :: BSD License
Requires-Dist: cffi (>=1.0.0)
Provides-Extra: all
Requires-Dist: pytest (>=3.8.0) ; extra == 'all'
Requires-Dist: pywin32 ; extra == 'all'
Provides-Extra: test
Requires-Dist: pytest (>=3.8.0) ; extra == 'test'
Requires-Dist: pywin32 ; extra == 'test'
Provides-Extra: tests
Requires-Dist: pytest (>=3.8.0) ; extra == 'tests'
Requires-Dist: pywin32 ; extra == 'tests'
